{
  "type": "FeatureCollection",
  "features": [
    {
      "type": "Feature",
      "properties": {
        "marker-color": "#7e7e7e",
        "marker-size": "medium",
        "marker-symbol": "",
        "name": "MadeUpbar"
      },
      "geometry": {
        "type": "Point",
        "coordinates": [
          144.9755859375,
          -37.768000831567605
        ]
      }
    }
  ]
}
